pago46/__init__.py
pago46/client.py
pago46/utils.py
pago46/tests/__init__.py
pago46/tests/test.py
pago46-0.0.2.dist-info/LICENSE.txt
pago46-0.0.2.dist-info/METADATA
pago46-0.0.2.dist-info/WHEEL
pago46-0.0.2.dist-info/top_level.txt
pago46-0.0.2.dist-info/RECORD
