Metadata-Version: 2.1
Name: pago46
Version: 0.0.2
Summary: Integraton package of pago46
Home-page: UNKNOWN
Author: Pago 46
Author-email: admin@46degrees.net
Maintainer: David Liencura
Maintainer-email: dliencura@46degrees.net
License: GPLv3
Keywords: pago46,chile,payments
Platform: UNKNOWN
Classifier: Intended Audience :: Developers
Classifier: Programming Language :: Python
Classifier: Programming Language :: Python :: 3
Classifier: Operating System :: OS Independent
Classifier: License :: OSI Approved :: GNU General Public License v3 (GPLv3)
Requires-Dist: requests (>=2.19.1)
